sanyamuvpackage/__init__.py
sanyamuvpackage/calculator.py
sanyamuvpackage/server.py
sanyamuvpackage-0.1.1.dist-info/METADATA
sanyamuvpackage-0.1.1.dist-info/WHEEL
sanyamuvpackage-0.1.1.dist-info/entry_points.txt
sanyamuvpackage-0.1.1.dist-info/RECORD
