Metadata-Version: 2.4
Name: sanyamuvpackage
Version: 0.1.1
Summary: Sanyam Testing app
Author-email: Sayyam-Karnavat <sanyam.karnavat5@gmail.com>
Requires-Python: >=3.10
Requires-Dist: flask>=3.1.1
